fantasy/__init__.py
fantasy/api_client.py
fantasy/client.py
fantasy/api_models/__init__.py
fantasy/api_models/auth.py
fantasy/api_models/drivers_and_constructors.py
fantasy/api_models/encoder.py
fantasy/api_models/homestats.py
fantasy/api_models/list_user_teams.py
fantasy/api_models/user_game_days.py
fantasy/api_models/leagues/__init__.py
fantasy/api_models/leagues/classic_private_league.py
fantasy/api_models/leagues/featured_leagues.py
fantasy/api_models/leagues/head_2_head.py
fantasy/api_models/leagues/pinned_leagues.py
fantasy/api_models/leagues/private_league_leaderboard.py
fantasy/api_models/leagues/public_classic_league.py
fantasy/api_models/leagues/public_leagues.py
fantasy/api_models/leagues/specific_leagues.py
fantasy/api_models/leagues/user_leagues.py
fantasy/models/__init__.py
fantasy/models/leagues/__init__.py
fantasy/models/leagues/private_leaderboard.py
fantasy/models/leagues/user_leagues.py
skelmis_f1_fantasy-0.2.0.dist-info/METADATA
skelmis_f1_fantasy-0.2.0.dist-info/WHEEL
skelmis_f1_fantasy-0.2.0.dist-info/licenses/LICENSE
skelmis_f1_fantasy-0.2.0.dist-info/RECORD
