Metadata-Version: 2.4
Name: skelmis-f1-fantasy
Version: 0.2.0
Summary: A performant, typed API for the Formula 1 Fantasy game .
Author-email: skelmis <skelmis.craft@gmail.com>
License-Expression: MIT
License-File: LICENSE
Classifier: Development Status :: 3 - Alpha
Classifier: License :: OSI Approved :: MIT License
Classifier: Operating System :: OS Independent
Classifier: Programming Language :: Python :: 3
Requires-Python: >=3.13
Requires-Dist: httpx>=0.28.1
Requires-Dist: pydantic>=2.11.3
Requires-Dist: skelmis-commons>=1.5.2
